outline/__init__.py
outline/outline.py
outline_manager-0.0.2.dist-info/LICENSE
outline_manager-0.0.2.dist-info/METADATA
outline_manager-0.0.2.dist-info/WHEEL
outline_manager-0.0.2.dist-info/top_level.txt
outline_manager-0.0.2.dist-info/RECORD
