Metadata-Version: 2.1
Name: outline-manager
Version: 0.0.2
Summary: Manages access keys for servers with Outline server installed.
Home-page: https://github.com/youngchingjui/pyoutline
Author: Ching Jui Young
Author-email: young.chingjui@youngandai.com
License: UNKNOWN
Platform: UNKNOWN
Classifier: Programming Language :: Python :: 3
Classifier: License :: OSI Approved :: MIT License
Classifier: Operating System :: OS Independent
Requires-Python: >=3.7
Requires-Dist: requests
